ai_integration/__init__.py
ai_integration/fake_inference_function.py
ai_integration/image_helpers.py
ai_integration/internal_methods.py
ai_integration/public_interface.py
ai_integration/modes/__init__.py
ai_integration/modes/command_line.py
ai_integration/modes/http.py
ai_integration/modes/testing_modes.py
ai_integration/modes/http_helpers/deepai.js
ai_integration/modes/http_helpers/deepai.min.js
ai_integration-1.0.16.dist-info/LICENSE
ai_integration-1.0.16.dist-info/METADATA
ai_integration-1.0.16.dist-info/WHEEL
ai_integration-1.0.16.dist-info/top_level.txt
ai_integration-1.0.16.dist-info/RECORD
