Metadata-Version: 2.1
Name: ai-integration
Version: 1.0.16
Summary: AI Model Integration for python
Home-page: https://github.com/deepai-org/ai_integration
Author: Deep AI, Inc
Author-email: admin@deepai.org
License: Apache 2.0
Platform: UNKNOWN
Classifier: Programming Language :: Python :: 2.7
Classifier: Programming Language :: Python :: 3
Classifier: Programming Language :: Python :: 3.7
Requires-Dist: Pillow
Requires-Dist: Flask
